kithairon/__init__.py
kithairon/_util.py
kithairon/labware.py
kithairon/picklists.py
kithairon/py.typed
kithairon/surveys/__init__.py
kithairon/surveys/platesurvey.py
kithairon/surveys/surveydata.py
kithairon/surveys/surveyreport.py
kithairon-0.2.0.dist-info/LICENCE.txt
kithairon-0.2.0.dist-info/METADATA
kithairon-0.2.0.dist-info/WHEEL
kithairon-0.2.0.dist-info/top_level.txt
kithairon-0.2.0.dist-info/RECORD
