Metadata-Version: 2.1
Name: kithairon
Version: 0.2.0
Summary: A library for the Echo liquid handler.
Author-email: Constantine Evans <const@costi.net>
License: EUROPEAN UNION PUBLIC LICENCE v. 1.2
Project-URL: Homepage, https://github.com/cgevans/kithairon
Project-URL: Documentation, https://kithairon.readthedocs.io/en/latest/
Classifier: Development Status :: 2 - Pre-Alpha
Classifier: Programming Language :: Python
Classifier: Intended Audience :: Science/Research
Classifier: Natural Language :: English
Classifier: License :: OSI Approved :: European Union Public Licence 1.2 (EUPL 1.2)
Classifier: Topic :: Scientific/Engineering
Classifier: Topic :: Scientific/Engineering :: Chemistry
Classifier: Topic :: Scientific/Engineering :: Physics
Classifier: Typing :: Typed
Classifier: Programming Language :: Python :: 3.10
Classifier: Programming Language :: Python :: 3.11
Classifier: Programming Language :: Python :: 3.12
License-File: LICENCE.txt
Requires-Dist: polars >0.19
Requires-Dist: numpy >=1
Requires-Dist: pydantic-xml ~=2.9
Requires-Dist: typing-extensions ~=4.4
Requires-Dist: lxml >=4.9
Requires-Dist: rich >=13
Requires-Dist: xdg-base-dirs
Requires-Dist: networkx >=3.2
Provides-Extra: all
Requires-Dist: kithairon[graphics] ; extra == 'all'
Provides-Extra: docs
Requires-Dist: kithairon[all] ; extra == 'docs'
Requires-Dist: sphinx ~=7.2 ; extra == 'docs'
Requires-Dist: numpydoc ~=1.6 ; extra == 'docs'
Requires-Dist: pydata-sphinx-theme ~=0.14 ; extra == 'docs'
Requires-Dist: autodocsumm ~=0.2 ; extra == 'docs'
Requires-Dist: autodoc-pydantic ~=2.0 ; extra == 'docs'
Requires-Dist: sphinx-book-theme ; extra == 'docs'
Requires-Dist: sphinx-autoapi ; extra == 'docs'
Provides-Extra: graphics
Requires-Dist: seaborn >=0.13 ; extra == 'graphics'
Provides-Extra: testing
Requires-Dist: kithairon[all] ; extra == 'testing'
Requires-Dist: pytest ~=7.4 ; extra == 'testing'
Requires-Dist: pytest-cov ~=4.1 ; extra == 'testing'
Requires-Dist: hypothesis ~=6.0 ; extra == 'testing'
